{"pieCharts": {"entity-gender": {"title": "Gender", "values": [94.93, 3.83, 1.24], "labels": ["male", "female", "<empty>"]}, "entity-ethnic_group": {"title": "Ethnic Group", "values": [85.61, 5.29, 2.35, 1.8, 1.08, 3.8499999999999974], "labels": ["<empty>", "African Americans", "English American", "Scotch-Irish Americans", "Americans", "other"]}, "entity-occupation": {"title": "Occupation", "values": [24.69, 10.52, 4.51, 4.48, 3.71, 51.96000000000004], "labels": ["politician", "military officer", "<empty>", "explorer", "lawyer", "other"]}}, "frequencies": [{"title": "Top 10 values for \"Events\"", "rows": [["The Civil War", "13,289"], ["World War II", "7,898"], ["Revolutionary War", "5,381"], ["World War I", "5,337"], ["The Vietnam War", "1,163"], ["The War of 1812", "1,051"], ["The Great Depression", "967"], ["Korean War", "726"], ["The Texas Revolution", "598"], ["Mexican War", "532"]], "cols": ["Value", "Count"], "resourceLink": "entities_type_EVENT.csv"}, {"title": "Top 10 values for \"Nationalities or religious or political groups\"", "rows": [["African-American", "6,795"], ["Native Americans", "2,647"], ["North American", "274"], ["All-American", "250"], ["Japanese American", "205"], ["Spanish-American", "199"], ["American Indians", "157"], ["Roman Catholic", "148"], ["Mexican-American", "133"], ["Anglo-American", "124"]], "cols": ["Value", "Count"], "resourceLink": "entities_type_NORP.csv"}, {"title": "Top 10 values for \"Organizations\"", "rows": [["The National Register of Places", "4,007"], ["The U.S. Army", "2,162"], ["United States Department", "1,529"], ["The National Park Service", "1,138"], ["The First Baptist Church", "1,064"], ["The Interior National Park Service Washington District", "1,039"], ["The Union Army", "1,018"], ["The U.S. Post Office", "862"], ["U.S. Navy", "848"], ["First Presbyterian Church", "789"]], "cols": ["Value", "Count"], "resourceLink": "entities_type_ORG.csv"}, {"title": "Top 10 values for \"People\"", "rows": [["George Washington", "2,534"], ["Abraham Lincoln", "2,041"], ["Robert E. Lee", "1,457"], ["John E. Smith", "858"], ["Thomas Jefferson", "710"], ["Andrew Jackson", "692"], ["Queen Anne", "662"], ["Sam Houston", "657"], ["Martin Luther King Jr.", "640"], ["Jefferson Davis", "599"]], "cols": ["Value", "Count"], "resourceLink": "entities_type_PERSON.csv"}]}